arktos/__init__.py
arktos-0.0.3.dist-info/LICENSE
arktos-0.0.3.dist-info/METADATA
arktos-0.0.3.dist-info/WHEEL
arktos-0.0.3.dist-info/top_level.txt
arktos-0.0.3.dist-info/RECORD
