Metadata-Version: 2.1
Name: arktos
Version: 0.0.3
Summary: A brief description of Arktos
Home-page: https://github.com/yourusername/arktos
Author: W Robert Long
Author-email: longrob604@gmail.com
License: UNKNOWN
Platform: UNKNOWN
